livekit/agents/__init__.py
livekit/agents/apipe.py
livekit/agents/consts.py
livekit/agents/exceptions.py
livekit/agents/http_server.py
livekit/agents/ipc_enc.py
livekit/agents/job_context.py
livekit/agents/job_request.py
livekit/agents/log.py
livekit/agents/plugin.py
livekit/agents/py.typed
livekit/agents/vad.py
livekit/agents/version.py
livekit/agents/worker.py
livekit/agents/cli/__init__.py
livekit/agents/cli/cli.py
livekit/agents/cli/log.py
livekit/agents/cli/protocol.py
livekit/agents/cli/watcher.py
livekit/agents/ipc/__init__.py
livekit/agents/ipc/consts.py
livekit/agents/ipc/job_main.py
livekit/agents/ipc/job_process.py
livekit/agents/ipc/protocol.py
livekit/agents/llm/__init__.py
livekit/agents/llm/_oai_api.py
livekit/agents/llm/chat_context.py
livekit/agents/llm/function_context.py
livekit/agents/llm/llm.py
livekit/agents/stt/__init__.py
livekit/agents/stt/stream_adapter.py
livekit/agents/stt/stt.py
livekit/agents/tokenize/__init__.py
livekit/agents/tokenize/_basic_hyphenator.py
livekit/agents/tokenize/_basic_paragraph.py
livekit/agents/tokenize/_basic_sent.py
livekit/agents/tokenize/_basic_word.py
livekit/agents/tokenize/basic.py
livekit/agents/tokenize/token_stream.py
livekit/agents/tokenize/tokenizer.py
livekit/agents/transcription/__init__.py
livekit/agents/transcription/_utils.py
livekit/agents/transcription/stt_forwarder.py
livekit/agents/transcription/tts_forwarder.py
livekit/agents/tts/__init__.py
livekit/agents/tts/stream_adapter.py
livekit/agents/tts/tts.py
livekit/agents/utils/__init__.py
livekit/agents/utils/event_emitter.py
livekit/agents/utils/exp_filter.py
livekit/agents/utils/http_context.py
livekit/agents/utils/log.py
livekit/agents/utils/misc.py
livekit/agents/utils/moving_average.py
livekit/agents/utils/aio/__init__.py
livekit/agents/utils/aio/channel.py
livekit/agents/utils/aio/debug.py
livekit/agents/utils/aio/interval.py
livekit/agents/utils/aio/select.py
livekit/agents/utils/aio/sleep.py
livekit/agents/utils/aio/task_set.py
aeon_agents-0.7.2.dist-info/METADATA
aeon_agents-0.7.2.dist-info/WHEEL
aeon_agents-0.7.2.dist-info/top_level.txt
aeon_agents-0.7.2.dist-info/RECORD
